voldiscount/__init__.py
voldiscount/calibration.py
voldiscount/data.py
voldiscount/interpolation.py
voldiscount/models.py
voldiscount/pair_selection.py
voldiscount/vol_params.py
voldiscount/voldiscount.py
voldiscount-0.1.4.dist-info/licenses/LICENSE
voldiscount-0.1.4.dist-info/METADATA
voldiscount-0.1.4.dist-info/WHEEL
voldiscount-0.1.4.dist-info/top_level.txt
voldiscount-0.1.4.dist-info/RECORD
