Metadata-Version: 2.4
Name: voldiscount
Version: 0.1.4
Summary: Extract discount rates from option data using Put-Call parity.
Home-page: https://github.com/GBERESEARCH/voldiscount
Author: GBERESEARCH
Author-email: gberesearch@gmail.com
License: MIT
License-File: LICENSE
Requires-Dist: numpy>=2.2.3
Requires-Dist: pandas>=2.2.3
Requires-Dist: scipy>=1.15.2
Requires-Dist: yfinance>=0.2.54
Requires-Dist: fastapi>=0.115.11
Requires-Dist: uvicorn>=0.34.0
Requires-Dist: python-multipart>=0.0.20
Requires-Dist: pydantic>=2.10.6
Requires-Dist: requests>=2.32.3
Dynamic: license-file
